unienv_playground/__init__.py
unienv_playground/wrapper/playground_compat.py
unienv_playground-0.0.1a1.dist-info/METADATA
unienv_playground-0.0.1a1.dist-info/WHEEL
unienv_playground-0.0.1a1.dist-info/top_level.txt
unienv_playground-0.0.1a1.dist-info/RECORD
